LICENSE
MANIFEST.in
README.md
VERSION
requirements.txt
setup.cfg
setup.py
powerful_pipes_log_viewer/__init__.py
powerful_pipes_log_viewer/__main__.py
powerful_pipes_log_viewer.egg-info/PKG-INFO
powerful_pipes_log_viewer.egg-info/SOURCES.txt
powerful_pipes_log_viewer.egg-info/dependency_links.txt
powerful_pipes_log_viewer.egg-info/entry_points.txt
powerful_pipes_log_viewer.egg-info/requires.txt
powerful_pipes_log_viewer.egg-info/top_level.txt
powerful_pipes_log_viewer.egg-info/zip-safe
powerful_pipes_log_viewer/action_help/__init__.py
powerful_pipes_log_viewer/action_help/action.py
powerful_pipes_log_viewer/action_help/setup.py
powerful_pipes_log_viewer/action_list/__init__.py
powerful_pipes_log_viewer/action_list/action.py
powerful_pipes_log_viewer/action_list/models.py
powerful_pipes_log_viewer/action_list/setup.py
powerful_pipes_log_viewer/action_show/__init__.py
powerful_pipes_log_viewer/action_show/action.py
powerful_pipes_log_viewer/action_show/models.py
powerful_pipes_log_viewer/action_show/setup.py
powerful_pipes_log_viewer/core/__init__.py
powerful_pipes_log_viewer/core/click_utils.py
powerful_pipes_log_viewer/core/file_utils.py
powerful_pipes_log_viewer/core/models.py