Metadata-Version: 2.1
Name: powerful-pipes-log-viewer
Version: 1.0.0
Summary: Powerful pipes log viewer
Home-page: https://github.com/42Crunch/powerful-pipes-log-viewer
Author: 42Crunch Research Team
Author-email: dev@42crunch.com
License: License :: OSI Approved :: Apache Software License
Platform: UNKNOWN
Classifier: License :: OSI Approved :: Apache Software License
Classifier: Programming Language :: Python :: 3.8
Classifier: Programming Language :: Python :: 3.9
Classifier: Programming Language :: Python :: 3.10
Classifier: Environment :: Console
Classifier: Operating System :: POSIX
Classifier: Operating System :: MacOS
Classifier: Operating System :: OS Independent
Classifier: Operating System :: Microsoft :: Windows
Classifier: Intended Audience :: Other Audience
Classifier: Intended Audience :: System Administrators
